oshepherd/__init__.py
oshepherd/cli.py
oshepherd/api/__init__.py
oshepherd/api/app.py
oshepherd/api/config.py
oshepherd/api/health.py
oshepherd/api/network_data.py
oshepherd/api/server.py
oshepherd/api/utils.py
oshepherd/api/chat/__init__.py
oshepherd/api/chat/models.py
oshepherd/api/chat/routes.py
oshepherd/api/embeddings/__init__.py
oshepherd/api/embeddings/models.py
oshepherd/api/embeddings/routes.py
oshepherd/api/generate/__init__.py
oshepherd/api/generate/models.py
oshepherd/api/generate/routes.py
oshepherd/api/tags/__init__.py
oshepherd/api/tags/models.py
oshepherd/api/tags/routes.py
oshepherd/api/version/__init__.py
oshepherd/api/version/models.py
oshepherd/api/version/routes.py
oshepherd/worker/__init__.py
oshepherd/worker/app.py
oshepherd/worker/config.py
oshepherd/worker/ollama_task.py
oshepherd/worker/tasks.py
oshepherd/worker/worker_data.py
oshepherd-0.0.18.dist-info/licenses/LICENSE
oshepherd-0.0.18.dist-info/METADATA
oshepherd-0.0.18.dist-info/WHEEL
oshepherd-0.0.18.dist-info/entry_points.txt
oshepherd-0.0.18.dist-info/top_level.txt
oshepherd-0.0.18.dist-info/RECORD
