Metadata-Version: 2.4
Name: oshepherd
Version: 0.0.18
Summary: The Oshepherd guiding the Ollama(s) inference orchestration.
Author: mnemonica.ai
Author-email: "mnemonica.ai" <info@mnemonica.ai>
Project-URL: Homepage, https://github.com/mnemonica-ai/oshepherd
Project-URL: Issues, https://github.com/mnemonica-ai/oshepherd/issues
Classifier: Programming Language :: Python :: 3
Classifier: License :: OSI Approved :: MIT License
Classifier: Operating System :: OS Independent
Requires-Python: >=3.12
License-File: LICENSE
Requires-Dist: gunicorn
Requires-Dist: fastapi[standard]
Requires-Dist: celery
Requires-Dist: click
Requires-Dist: ollama
Requires-Dist: amqp
Requires-Dist: redis
Requires-Dist: pydantic
Requires-Dist: python-dotenv
Requires-Dist: requests
Provides-Extra: dev
Requires-Dist: packageName[lint,tests]; extra == "dev"
Requires-Dist: build; extra == "dev"
Requires-Dist: twine; extra == "dev"
Provides-Extra: tests
Requires-Dist: pytest; extra == "tests"
Provides-Extra: lint
Requires-Dist: black; extra == "lint"
Dynamic: author
Dynamic: license-file
Dynamic: requires-python
